CHANGELOG.md
LICENSE
README.md
sus/__init__.py
sus/dumper.py
sus/loader.py
sus/schemas.py
sus_io-0.2.1.dist-info/entry_points.txt
sus_io-0.2.1.dist-info/LICENSE
sus_io-0.2.1.dist-info/WHEEL
sus_io-0.2.1.dist-info/METADATA
sus_io-0.2.1.dist-info/RECORD
