Metadata-Version: 2.1
Name: sus-io
Version: 0.2.1
Summary: A SUS (Sliding Universal Score) parser and generator.
Home-page: https://github.com/mkpoli/sus-io#readme
License: MIT
Keywords: sus,pjsekai,chunithm,seaurchin
Author: mkpoli
Author-email: mkpoli@mkpo.li
Requires-Python: >=3.9,<4.0
Classifier: Development Status :: 3 - Alpha
Classifier: Intended Audience :: Developers
Classifier: License :: OSI Approved :: MIT License
Classifier: Programming Language :: Python :: 3
Classifier: Programming Language :: Python :: 3.10
Classifier: Programming Language :: Python :: 3.9
Classifier: Topic :: Games/Entertainment :: Arcade
Classifier: Topic :: Utilities
Requires-Dist: base36 (>=0.1.1,<0.2.0)
Requires-Dist: dataclasses-json (>=0.5.6,<0.6.0)
Requires-Dist: single-source (>=0.2.0,<0.3.0)
Project-URL: Bug Tracker, https://github.com/mkpoli/sus-io/issues
Project-URL: Changelog, https://github.com/mkpoli/sus-io/blob/main/CHANGELOG.md
Project-URL: Repository, https://github.com/mkpoli/sus-io
